LICENSE.rst
LICENSE_GPL.rst
MANIFEST.in
README.rst
setup.py
src/agx/__init__.py
src/agx.generator.sql.egg-info/PKG-INFO
src/agx.generator.sql.egg-info/SOURCES.txt
src/agx.generator.sql.egg-info/dependency_links.txt
src/agx.generator.sql.egg-info/entry_points.txt
src/agx.generator.sql.egg-info/namespace_packages.txt
src/agx.generator.sql.egg-info/not-zip-safe
src/agx.generator.sql.egg-info/requires.txt
src/agx.generator.sql.egg-info/top_level.txt
src/agx/generator/__init__.py
src/agx/generator/sql/__init__.py
src/agx/generator/sql/configure.zcml
src/agx/generator/sql/generator.py
src/agx/generator/sql/generator.rst
src/agx/generator/sql/profiles.py
src/agx/generator/sql/scope.py
src/agx/generator/sql/tests.py
src/agx/generator/sql/profiles/sql.profile.di
src/agx/generator/sql/profiles/sql.profile.notation
src/agx/generator/sql/profiles/sql.profile.uml
src/agx/generator/sql/resources/model_templates/sql_example/manifest.txt
src/agx/generator/sql/resources/model_templates/sql_example/model.di
src/agx/generator/sql/resources/model_templates/sql_example/model.notation
src/agx/generator/sql/resources/model_templates/sql_example/model.uml
src/agx/generator/sql/resources/model_templates/sql_example/model.uml.agx
src/agx/generator/sql/resources/model_templates/sql_example/uml_profiles/pyegg.profile.uml
src/agx/generator/sql/resources/model_templates/sql_example/uml_profiles/sql.profile.uml
src/agx/generator/sql/resources/profiles/sql.profile.uml
src/agx/generator/sql/templates/README-sqlalchemy.rst.jinja
src/agx/generator/sql/templates/orderedcollection.py.jinja
src/agx/generator/sql/testing/__init__.py
src/agx/generator/sql/testing/data/agx.generator.sql-sample.di
src/agx/generator/sql/testing/data/agx.generator.sql-sample.notation
src/agx/generator/sql/testing/data/agx.generator.sql-sample.uml
src/agx/generator/sql/testing/data/agx.generator.sql-sample.uml.agx
src/agx/generator/sql/testing/data/agx.generator.sql-sample/LICENSE.rst
src/agx/generator/sql/testing/data/agx.generator.sql-sample/MANIFEST.rst
src/agx/generator/sql/testing/data/agx.generator.sql-sample/README.rst
src/agx/generator/sql/testing/data/agx.generator.sql-sample/setup.py
src/agx/generator/sql/testing/data/agx.generator.sql-sample/src/agx/__init__.py
src/agx/generator/sql/testing/data/agx.generator.sql-sample/src/agx/testpackage/__init__.py
